dbt_dry_run/__init__.py
dbt_dry_run/__main__.py
dbt_dry_run/adapter/__init__.py
dbt_dry_run/adapter/service.py
dbt_dry_run/adapter/utils.py
dbt_dry_run/cli.py
dbt_dry_run/columns_metadata.py
dbt_dry_run/exception.py
dbt_dry_run/execution.py
dbt_dry_run/flags.py
dbt_dry_run/linting/__init__.py
dbt_dry_run/linting/column_linting.py
dbt_dry_run/models/__init__.py
dbt_dry_run/models/dry_run_result.py
dbt_dry_run/models/manifest.py
dbt_dry_run/models/profile.py
dbt_dry_run/models/report.py
dbt_dry_run/models/table.py
dbt_dry_run/node_dispatch.py
dbt_dry_run/node_runner/__init__.py
dbt_dry_run/node_runner/incremental_runner.py
dbt_dry_run/node_runner/node_test_runner.py
dbt_dry_run/node_runner/seed_runner.py
dbt_dry_run/node_runner/snapshot_runner.py
dbt_dry_run/node_runner/source_runner.py
dbt_dry_run/node_runner/table_runner.py
dbt_dry_run/node_runner/view_runner.py
dbt_dry_run/result_reporter.py
dbt_dry_run/results.py
dbt_dry_run/scheduler.py
dbt_dry_run/schema_change_handlers.py
dbt_dry_run/sql/__init__.py
dbt_dry_run/sql/literals.py
dbt_dry_run/sql/parsing.py
dbt_dry_run/sql/statements.py
dbt_dry_run/sql_runner/__init__.py
dbt_dry_run/sql_runner/big_query_sql_runner.py
dbt_dry_run/test/__init__.py
dbt_dry_run/test/conftest.py
dbt_dry_run/test/linting/__init__.py
dbt_dry_run/test/linting/test_column_linting.py
dbt_dry_run/test/models/__init__.py
dbt_dry_run/test/models/test_manifest.py
dbt_dry_run/test/models/test_profile.py
dbt_dry_run/test/node_runner/__init__.py
dbt_dry_run/test/node_runner/test_incremental_runner.py
dbt_dry_run/test/node_runner/test_node_runner.py
dbt_dry_run/test/node_runner/test_seed_runner.py
dbt_dry_run/test/node_runner/test_snapshot_runner.py
dbt_dry_run/test/node_runner/test_source_runner.py
dbt_dry_run/test/node_runner/test_table_runner.py
dbt_dry_run/test/node_runner/test_test_runner.py
dbt_dry_run/test/node_runner/test_view_runner.py
dbt_dry_run/test/sql/__init__.py
dbt_dry_run/test/sql/test_literals.py
dbt_dry_run-0.8.6.dist-info/METADATA
dbt_dry_run-0.8.6.dist-info/WHEEL
dbt_dry_run-0.8.6.dist-info/entry_points.txt
dbt_dry_run-0.8.6.dist-info/licenses/LICENSE
dbt_dry_run-0.8.6.dist-info/RECORD
