Metadata-Version: 2.4
Name: dbt-dry-run
Version: 0.8.6
Summary: Dry run dbt projects
License: Apache-2.0
License-File: LICENSE
Author: Connor Charles
Author-email: connor.charles@autotrader.co.uk
Requires-Python: >=3.10,<3.15
Classifier: License :: OSI Approved :: Apache Software License
Classifier: Programming Language :: Python :: 3
Classifier: Programming Language :: Python :: 3.10
Classifier: Programming Language :: Python :: 3.11
Classifier: Programming Language :: Python :: 3.12
Classifier: Programming Language :: Python :: 3.13
Classifier: Programming Language :: Python :: 3.14
Requires-Dist: agate (>=1.7.0,<1.10)
Requires-Dist: google-cloud-bigquery (>=3,<4)
Requires-Dist: networkx (>=2.3,<4.0)
Requires-Dist: pydantic (<3)
Requires-Dist: pyyaml (>=6,<7)
Requires-Dist: tenacity (>=8.2,<9.0)
Requires-Dist: typer (>=0,<1)
Project-URL: Repository, https://github.com/autotraderuk/dbt-dry-run
